PyCertify/__init__.py
PyCertify/intc_function.py
PyCertify-0.0.6.dist-info/LICENSE.txt
PyCertify-0.0.6.dist-info/METADATA
PyCertify-0.0.6.dist-info/WHEEL
PyCertify-0.0.6.dist-info/top_level.txt
PyCertify-0.0.6.dist-info/RECORD
