Metadata-Version: 2.1
Name: PyCertify
Version: 0.0.6
Summary: Package to certify variables
Author: Ishan Jain
Author-email: ishanjain0421@gmail.com
Keywords: python,qol,validation,input
Classifier: Development Status :: 3 - Alpha
Classifier: Intended Audience :: Education
Classifier: Programming Language :: Python :: 3
Classifier: Operating System :: Microsoft :: Windows
License-File: LICENSE.txt
